PyShbak/Normalization.py
PyShbak/Processor.py
PyShbak/TweetsCleaner.py
PyShbak/__init__.py
PyShbak/ar.py
PyShbak/cleaningtext.py
PyShbak/en.py
PyShbak/general.py
PyShbak-0.3.dist-info/LICENSE.txt
PyShbak-0.3.dist-info/METADATA
PyShbak-0.3.dist-info/WHEEL
PyShbak-0.3.dist-info/top_level.txt
PyShbak-0.3.dist-info/RECORD
