Metadata-Version: 2.1
Name: PyShbak
Version: 0.3
Summary: SHAWPACK NLP processing package
Home-page: https://github.com/AbdelrahmanShahrour/PyShbak
Author: AbdelrahmanShahrour
License: UNKNOWN
Keywords: NLP,text-data,AI,DS,Shahrour,arabic-py,arabic-nlp
Platform: UNKNOWN
Classifier: Programming Language :: Python :: 3
Classifier: License :: OSI Approved :: MIT License
Classifier: Operating System :: OS Independent
License-File: LICENSE.txt
Requires-Dist: click (==8.1.3)
Requires-Dist: joblib (==1.2.0)
Requires-Dist: nltk (==3.7)
Requires-Dist: regex (==2022.10.31)
Requires-Dist: tqdm (==4.64.1)
